easy_translation/__init__.py
easy_translation/glossary.py
easy_translation/translation.py
easy_translation/util.py
easy_translation-0.3.0.data/scripts/et
easy_translation-0.3.0.dist-info/LICENSE.md
easy_translation-0.3.0.dist-info/METADATA
easy_translation-0.3.0.dist-info/WHEEL
easy_translation-0.3.0.dist-info/top_level.txt
easy_translation-0.3.0.dist-info/RECORD
