Metadata-Version: 2.1
Name: easy-translation
Version: 0.3.0
Summary: A quick Chinese<->English translation
Home-page: https://github.com/zhengxu001/easy_translation
Author: Xu Zheng
Author-email: zhengxu5511@gmail.com
License-File: LICENSE.md
Requires-Dist: googletrans (==4.0.0rc1)
